depio/BuildMode.py
depio/Executors.py
depio/Pipeline.py
depio/Task.py
depio/TaskStatus.py
depio/decorators.py
depio/exceptions.py
depio/file_helpers.py
depio/logging.py
depio/stdio_helpers.py
depio-0.1.2.dist-info/licenses/LICENSE
depio-0.1.2.dist-info/METADATA
depio-0.1.2.dist-info/WHEEL
depio-0.1.2.dist-info/top_level.txt
depio-0.1.2.dist-info/RECORD
