Metadata-Version: 2.4
Name: depio
Version: 0.1.2
Summary: A simple task manager with slurm integration
Author-email: Maximilian Noppel <noppel@kit.edu>
Project-URL: Homepage, https://github.com/noppelmax/depio
Project-URL: Issues, https://github.com/noppelmax/depio/issues
Classifier: Programming Language :: Python :: 3
Classifier: License :: OSI Approved :: GNU General Public License v3 (GPLv3)
Classifier: Operating System :: OS Independent
Requires-Python: >=3.9
License-File: LICENSE
Requires-Dist: tabulate
Requires-Dist: pytest
Requires-Dist: submitit
Requires-Dist: coverage
Requires-Dist: termcolor
Requires-Dist: attrs
Requires-Dist: rich<15.0.0,>=14.2.0
Dynamic: license-file
